{
  "timestamp": "2026-04-20 17:05:42 UTC",
  "results": [
    {
      "domain": "wdfiles.mirror.lestday233.eu.org",
      "location": "美国佛罗里达迈阿密",
      "ip": "64.29.17.1",
      "max": 287.96,
      "min": 13.02,
      "avg": 150.49,
      "responseTime": 1448,
      "success": true
    },
    {
      "domain": "img.mirror.lestday233.eu.org",
      "location": "美国",
      "ip": "216.198.79.1",
      "max": 76.34,
      "min": 10.15,
      "avg": 43.25,
      "responseTime": 404,
      "success": true
    },
    {
      "domain": "cdn.mirror.lestday233.eu.org",
      "location": "美国佛罗里达迈阿密",
      "ip": "64.29.17.65",
      "max": 289.25,
      "min": 20.01,
      "avg": 154.63,
      "responseTime": 1795,
      "success": true
    },
    {
      "domain": "wdfiles.mirror.backroomswiki.com",
      "location": "美国佛罗里达迈阿密",
      "ip": "64.29.17.1",
      "max": 185.6,
      "min": 10.72,
      "avg": 98.16,
      "responseTime": 472,
      "success": true
    },
    {
      "domain": "img.mirror.backroomswiki.com",
      "location": "美国佛罗里达迈阿密",
      "ip": "64.29.17.65",
      "max": 56.65,
      "min": 11,
      "avg": 33.83,
      "responseTime": 351,
      "success": true
    },
    {
      "domain": "cdn.mirror.backroomswiki.com",
      "location": "美国",
      "ip": "216.198.79.1",
      "max": 212.86,
      "min": 18.41,
      "avg": 115.64,
      "responseTime": 820,
      "success": true
    }
  ],
  "summary": {
    "total": 6,
    "success": 6,
    "failed": 0,
    "avgResponse": 99.33333333333333
  }
}