{
  "timestamp": "2026-04-02 02:29:26 UTC",
  "results": [
    {
      "domain": "wdfiles.mirror.lestday233.eu.org",
      "location": "美国佛罗里达迈阿密",
      "ip": "64.29.17.65",
      "max": 359.44,
      "min": 69.54,
      "avg": 214.49,
      "responseTime": 2128,
      "success": true
    },
    {
      "domain": "img.mirror.lestday233.eu.org",
      "location": "美国",
      "ip": "216.198.79.65",
      "max": 290.52,
      "min": 85.56,
      "avg": 188.04,
      "responseTime": 654,
      "success": true
    },
    {
      "domain": "cdn.mirror.lestday233.eu.org",
      "location": "美国",
      "ip": "216.198.79.1",
      "max": 140.36,
      "min": 15.38,
      "avg": 77.87,
      "responseTime": 555,
      "success": true
    },
    {
      "domain": "wdfiles.mirror.backroomswiki.com",
      "location": "美国",
      "ip": "216.198.79.1",
      "max": 68.62,
      "min": 17.99,
      "avg": 43.31,
      "responseTime": 327,
      "success": true
    },
    {
      "domain": "img.mirror.backroomswiki.com",
      "location": "美国",
      "ip": "216.198.79.1",
      "max": 97.3,
      "min": 15.89,
      "avg": 56.6,
      "responseTime": 680,
      "success": true
    },
    {
      "domain": "cdn.mirror.backroomswiki.com",
      "location": "美国",
      "ip": "216.198.79.1",
      "max": 103.88,
      "min": 41,
      "avg": 72.44,
      "responseTime": 795,
      "success": true
    }
  ],
  "summary": {
    "total": 6,
    "success": 6,
    "failed": 0,
    "avgResponse": 108.79166666666667
  }
}